<?xml version="1.0"?>
<house><frontdoor x="444" y="34" z="7"/><owner name=""/><subowner name="Archie"/><doorowner x="444" y="34" z="7" name="punjabiballer"/><doorowner x="444" y="34" z="7" name="     "/><doorowner x="444" y="34" z="7" name="   "/><doorowner x="444" y="34" z="7" name="   "/><doorowner x="444" y="34" z="7" name=" "/><doorowner x="444" y="34" z="7" name=" "/><doorowner x="444" y="34" z="7" name=" "/><doorowner x="444" y="34" z="7" name=" "/><doorowner x="444" y="34" z="7" name=" "/><doorowner x="444" y="34" z="7" name=" "/><doorowner x="444" y="34" z="7" name=" "/><doorowner x="444" y="34" z="7" name=" "/><doorowner x="444" y="34" z="7" name=" "/><doorowner x="444" y="34" z="7" name=" "/><doorowner x="444" y="34" z="7" name=" "/><doorowner x="444" y="34" z="7" name=" "/><doorowner x="444" y="34" z="7" name=" "/><doorowner x="444" y="34" z="7" name=" "/><doorowner x="444" y="34" z="7" name=" "/><doorowner x="444" y="34" z="7" name=" "/><doorowner x="444" y="34" z="7" name=" "/><doorowner x="444" y="34" z="7" name=" "/><doorowner x="444" y="34" z="7" name=" "/><doorowner x="444" y="34" z="7" name="punjabiballer"/></house>
